binloader/__init__.py
binloader/__main__.py
binloader/binaries/busybox_amd64
binloader/binaries/vim_amd64
binloader-0.0.3.dist-info/METADATA
binloader-0.0.3.dist-info/WHEEL
binloader-0.0.3.dist-info/top_level.txt
binloader-0.0.3.dist-info/RECORD
