Metadata-Version: 2.4
Name: binloader
Version: 0.0.3
Summary: Run VIM and Busybox. Optionally run remote binaries
Author-email: Ulises <ulises.odysseus22@gmail.com>
License: GPLv2
Project-URL: Homepage, https://github.com/ulisesojeda/binary_loader
Classifier: Operating System :: POSIX
Requires-Python: >=3.4
